MANIFEST.in
README.rst
setup.py
path_manifest.egg-info/PKG-INFO
path_manifest.egg-info/SOURCES.txt
path_manifest.egg-info/dependency_links.txt
path_manifest.egg-info/not-zip-safe
path_manifest.egg-info/top_level.txt
pm/__init__.py
pm/manifest.py
pm/utility.py
pm/config/__init__.py
pm/config/log.py
pm/config/patch.py
pm/resources/README.rst
pm/resources/requirements.txt
pm/resources/scripts/pm_check_for_changes
pm/resources/scripts/pm_make_differential_patch
pm/resources/scripts/pm_read_patch_info
pm/resources/scripts/pm_show_applied_patches
pm/resources/scripts/pm_write_manifest