Metadata-Version: 1.0
Name: path-manifest
Version: 0.2.20
Summary: Inject a manifest of a directory structure and generate patches against it later.
Home-page: https://github.com/dsoprea/PathManifest
Author: Dustin Oprea
Author-email: myselfasunder@gmail.com
License: GPL 2
Keywords: path manifest patch patches
Platform: UNKNOWN
